py_paginator
