Metadata-Version: 2.1
Name: py-paginator
Version: 1.0.2
Summary: Paginator to generate page numbers for pagination
Home-page: https://github.com/sujeetkv/py-paginator
Author: Sujeet Kumar
Author-email: sujeetkv90@gmail.com
License: MIT
Keywords: paginator py_paginator py-paginator
Platform: any
Classifier: Development Status :: 5 - Production/Stable
Classifier: Intended Audience :: Developers
Classifier: Programming Language :: Python
Classifier: Programming Language :: Python :: 2.7
Classifier: Programming Language :: Python :: 3.3
Classifier: Programming Language :: Python :: 3.4
Classifier: Programming Language :: Python :: 3.5
Classifier: Programming Language :: Python :: 3.6
Classifier: License :: OSI Approved :: MIT License
Classifier: Operating System :: OS Independent
Classifier: Topic :: Internet :: WWW/HTTP :: Dynamic Content :: Page Counters
Classifier: Topic :: Software Development :: Libraries :: Python Modules
Classifier: Topic :: Utilities
Requires-Python: >=2.7
